appbuilder/__init__.py
appbuilder/core/__init__.py
appbuilder/core/_client.py
appbuilder/core/_exception.py
appbuilder/core/_session.py
appbuilder/core/agent.py
appbuilder/core/component.py
appbuilder/core/constants.py
appbuilder/core/context.py
appbuilder/core/functional.py
appbuilder/core/message.py
appbuilder/core/session_message.py
appbuilder/core/user_session.py
appbuilder/core/utils.py
appbuilder/core/assistant/__init__.py
appbuilder/core/assistant/base.py
appbuilder/core/assistant/assistants/__init__.py
appbuilder/core/assistant/assistants/assistants.py
appbuilder/core/assistant/assistants/files.py
appbuilder/core/assistant/threads/__init__.py
appbuilder/core/assistant/threads/threads.py
appbuilder/core/assistant/threads/messages/__init__.py
appbuilder/core/assistant/threads/messages/messages.py
appbuilder/core/assistant/threads/runs/__init__.py
appbuilder/core/assistant/threads/runs/runs.py
appbuilder/core/assistant/threads/runs/steps.py
appbuilder/core/assistant/threads/runs/stream_helper.py
appbuilder/core/assistant/type/__init__.py
appbuilder/core/assistant/type/assistant_type.py
appbuilder/core/assistant/type/public_type.py
appbuilder/core/assistant/type/thread_type.py
appbuilder/core/components/__init__.py
appbuilder/core/components/animal_recognize/__init__.py
appbuilder/core/components/animal_recognize/component.py
appbuilder/core/components/animal_recognize/model.py
appbuilder/core/components/asr/__init__.py
appbuilder/core/components/asr/component.py
appbuilder/core/components/asr/model.py
appbuilder/core/components/dish_recognize/__init__.py
appbuilder/core/components/dish_recognize/component.py
appbuilder/core/components/dish_recognize/model.py
appbuilder/core/components/doc_crop_enhance/__init__.py
appbuilder/core/components/doc_crop_enhance/component.py
appbuilder/core/components/doc_crop_enhance/model.py
appbuilder/core/components/doc_format_converter/__init__.py
appbuilder/core/components/doc_format_converter/component.py
appbuilder_sdk-1.1.4.dist-info/licenses/LICENSE
appbuilder_sdk-1.1.4.dist-info/METADATA
appbuilder_sdk-1.1.4.dist-info/WHEEL
appbuilder_sdk-1.1.4.dist-info/entry_points.txt
appbuilder_sdk-1.1.4.dist-info/top_level.txt
appbuilder_sdk-1.1.4.dist-info/RECORD
